nc_py_install/__init__.py
nc_py_install/__main__.py
nc_py_install/_version.py
nc_py_install/api.py
nc_py_install/cli.py
nc_py_install-0.0.2.dist-info/LICENSE
nc_py_install-0.0.2.dist-info/METADATA
nc_py_install-0.0.2.dist-info/WHEEL
nc_py_install-0.0.2.dist-info/top_level.txt
nc_py_install-0.0.2.dist-info/zip-safe
nc_py_install-0.0.2.dist-info/RECORD
