Metadata-Version: 2.1
Name: nc-py-install
Version: 0.0.2
Summary: Python 3.9+ package for installing Nextcloud Python Framework
Home-page: https://github.com/cloud-py-api
Author: Alexander Piskun
Author-email: bigcat88@users.noreply.github.com
License: Apache-2.0
Project-URL: Source, https://github.com/cloud-py-api/nc-py-install
Project-URL: Changelog, https://github.com/cloud-py-api/nc-py-install/blob/master/CHANGELOG.md
Keywords: python,install,framework,nextcloud
Classifier: Development Status :: 2 - Pre-Alpha
Classifier: Intended Audience :: Developers
Classifier: Topic :: Software Development
Classifier: Topic :: System :: Installation/Setup
Classifier: Programming Language :: Python :: 3
Classifier: Programming Language :: Python :: 3.9
Classifier: Programming Language :: Python :: 3.10
Classifier: Programming Language :: Python :: 3.11
Classifier: Programming Language :: Python :: Implementation :: CPython
Classifier: Programming Language :: Python :: Implementation :: PyPy
Classifier: License :: OSI Approved :: Apache Software License
Classifier: Operating System :: OS Independent
Requires-Python: >=3.9
License-File: LICENSE
Requires-Dist: requirements-parser
Provides-Extra: dev
Requires-Dist: pre-commit ; extra == 'dev'
Requires-Dist: pytest ; extra == 'dev'
Requires-Dist: pylint ; extra == 'dev'
Requires-Dist: coverage ; extra == 'dev'
Provides-Extra: docs
Requires-Dist: sphinx (>=4.4) ; extra == 'docs'
Requires-Dist: sphinx-issues (>=3.0.1) ; extra == 'docs'
Requires-Dist: sphinx-rtd-theme (>=1.0) ; extra == 'docs'
Provides-Extra: tests
Requires-Dist: pytest ; extra == 'tests'
